{"credit":"MadewithBlockbench","texture_size":[36,36],"textures":{"0":"dove:block/rsjj/sign_14","particle":"dove:block/rsjj/sign_14"},"elements":[{"from":[7.25,0,13.25],"to":[8.75,24,14.75],"rotation":{"angle":0,"axis":"y","origin":[7,0,7]},"faces":{"north":{"uv":[0,4.44444,0.66667,15.11111],"texture":"#0"},"east":{"uv":[0,4.44444,0.66667,15.11111],"texture":"#0"},"south":{"uv":[0,4.44444,0.66667,15.11111],"texture":"#0"},"west":{"uv":[0,4.44444,0.66667,15.11111],"texture":"#0"},"up":{"uv":[10.88889,7.77778,10.22222,7.11111],"texture":"#0"},"down":{"uv":[10.88889,8,10.22222,8.66667],"texture":"#0"}}},{"from":[6.75,0,5],"to":[9.25,6.25,6.75],"rotation":{"angle":0,"axis":"y","origin":[7,0,-1]},"faces":{"north":{"uv":[3.55556,4.44444,4.66667,7.22222],"texture":"#0"},"east":{"uv":[5.33333,7.55556,6.11111,10.33333],"texture":"#0"},"south":{"uv":[3.55556,4.44444,4.66667,7.22222],"texture":"#0"},"west":{"uv":[8,0.88889,8.77778,3.66667],"texture":"#0"},"up":{"uv":[11.33333,1.66667,10.22222,0.88889],"texture":"#0"},"down":{"uv":[11.33333,1.77778,10.22222,2.55556],"texture":"#0"}}},{"from":[6.55,2.25,4.9],"to":[9.45,5,4.9],"rotation":{"angle":0,"axis":"y","origin":[7,0.5,-1.1]},"faces":{"north":{"uv":[12.55556,12.88889,14.55556,14.88889],"texture":"#0"}}},{"from":[6.0481,1.76229,5.025],"to":[8.3981,5.01229,6.725],"rotation":{"angle":45,"axis":"z","origin":[6.7231,3.38729,5.875]},"faces":{"north":{"uv":[8.88889,5.77778,9.88889,7.22222],"texture":"#0"},"south":{"uv":[9.88889,5.77778,8.88889,7.22222],"texture":"#0"},"west":{"uv":[8.88889,9.33333,9.66667,10.77778],"texture":"#0"},"up":{"uv":[11.22222,6.55556,10.22222,5.77778],"texture":"#0"}}},{"from":[5.74413,0.40444,5.05],"to":[6.69413,4.80444,6.7],"rotation":{"angle":22.5,"axis":"z","origin":[7.29413,2.80444,5.875]},"faces":{"north":{"uv":[9.77778,0.88889,10.22222,2.88889],"texture":"#0"},"south":{"uv":[10.22222,0.88889,9.77778,2.88889],"texture":"#0"},"west":{"uv":[8.88889,0.88889,9.66667,2.88889],"texture":"#0"}}},{"from":[7.6019,1.76229,5.025],"to":[9.9519,5.01229,6.725],"rotation":{"angle":-45,"axis":"z","origin":[9.2769,3.38729,5.875]},"faces":{"north":{"uv":[9.88889,5.77778,8.88889,7.22222],"texture":"#0"},"east":{"uv":[9.66667,9.33333,8.88889,10.77778],"texture":"#0"},"south":{"uv":[8.88889,5.77778,9.88889,7.22222],"texture":"#0"},"up":{"uv":[10.22222,6.55556,11.22222,5.77778],"texture":"#0"}}},{"from":[9.30587,0.40444,5.05],"to":[10.25587,4.80444,6.7],"rotation":{"angle":-22.5,"axis":"z","origin":[8.70587,2.80444,5.875]},"faces":{"north":{"uv":[10.22222,0.88889,9.77778,2.88889],"texture":"#0"},"east":{"uv":[9.66667,0.88889,8.88889,2.88889],"texture":"#0"},"south":{"uv":[9.77778,0.88889,10.22222,2.88889],"texture":"#0"}}},{"from":[7.65,6.25,2.25],"to":[8.35,7.25,13.25],"rotation":{"angle":0,"axis":"y","origin":[7,-4,5.5]},"faces":{"north":{"uv":[10.22222,9.77778,10.55556,10.22222],"texture":"#0"},"east":{"uv":[8,0,12.88889,0.44444],"texture":"#0"},"west":{"uv":[8,0.44444,12.88889,0.88889],"texture":"#0"},"up":{"uv":[8.33333,10.66667,8,5.77778],"texture":"#0"},"down":{"uv":[6.55556,8,6.22222,12.88889],"texture":"#0"}}},{"from":[7.4,7.25,4.25],"to":[8.6,8.25,13.25],"rotation":{"angle":0,"axis":"y","origin":[7,-3,5.5]},"faces":{"north":{"uv":[10.22222,8.88889,10.77778,9.33333],"texture":"#0"},"east":{"uv":[8,4,12,4.44444],"texture":"#0"},"west":{"uv":[8,4.44444,12,4.88889],"texture":"#0"},"up":{"uv":[6.77778,4,6.22222,0],"texture":"#0"},"down":{"uv":[6.77778,4,6.22222,8],"texture":"#0"}}},{"from":[7.4,19.25,4.25],"to":[8.6,20.25,13.25],"rotation":{"angle":0,"axis":"y","origin":[8,19.75,8.25]},"faces":{"north":{"uv":[10.22222,9.33333,10.77778,9.77778],"texture":"#0"},"east":{"uv":[8,4.88889,12,5.33333],"texture":"#0"},"west":{"uv":[8,5.33333,12,5.77778],"texture":"#0"},"up":{"uv":[7.66667,4,7.11111,0],"texture":"#0"},"down":{"uv":[7.66667,4,7.11111,8],"texture":"#0"}}},{"from":[7.55,8.25,4.625],"to":[8.45,19.25,5.375],"rotation":{"angle":0,"axis":"y","origin":[7,-2,6.875]},"faces":{"north":{"uv":[3.55556,7.55556,4,12.44444],"texture":"#0"},"east":{"uv":[7.11111,8,7.44444,12.88889],"texture":"#0"},"south":{"uv":[3.55556,7.55556,4,12.44444],"texture":"#0"},"west":{"uv":[7.11111,8,7.44444,12.88889],"texture":"#0"}}},{"from":[7.55,8.25,9.625],"to":[8.45,19.25,10.375],"rotation":{"angle":0,"axis":"y","origin":[7,-2,11.875]},"faces":{"north":{"uv":[3.55556,7.55556,4,12.44444],"texture":"#0"},"east":{"uv":[7.11111,8,7.44444,12.88889],"texture":"#0"},"south":{"uv":[3.55556,7.55556,4,12.44444],"texture":"#0"},"west":{"uv":[7.11111,8,7.44444,12.88889],"texture":"#0"}}},{"from":[2.05,20.25,3.75],"to":[8.3,20.75,13.25],"rotation":{"angle":22.5,"axis":"z","origin":[8.05,20,12.5]},"faces":{"north":{"uv":[10.22222,2.66667,13,2.88889],"texture":"#0"},"east":{"uv":[8.88889,3.11111,13.11111,3.33333],"texture":"#0"},"south":{"uv":[10.22222,6.66667,13,6.88889],"texture":"#0"},"west":{"uv":[8.88889,3.55556,13.11111,3.77778],"texture":"#0"},"up":{"uv":[2.77778,4.22222,0,0],"texture":"#0"},"down":{"uv":[5.55556,4.22222,2.77778,0],"texture":"#0"}}},{"from":[7.7,20.25,3.75],"to":[13.95,20.75,13.25],"rotation":{"angle":-22.5,"axis":"z","origin":[7.95,20,12.5]},"faces":{"north":{"uv":[13,2.66667,10.22222,2.88889],"texture":"#0"},"east":{"uv":[13.11111,3.55556,8.88889,3.77778],"texture":"#0"},"south":{"uv":[13,6.66667,10.22222,6.88889],"texture":"#0"},"west":{"uv":[13.11111,3.11111,8.88889,3.33333],"texture":"#0"},"up":{"uv":[0,4.22222,2.77778,0],"texture":"#0"},"down":{"uv":[2.77778,4.22222,5.55556,0],"texture":"#0"}}}],"gui_light":"front","display":{"thirdperson_righthand":{"rotation":[67.5,0,0],"translation":[0,3,1.75],"scale":[0.41406,0.41406,0.41406]},"thirdperson_lefthand":{"rotation":[67.5,0,0],"translation":[0,3,1.75],"scale":[0.41406,0.41406,0.41406]},"firstperson_righthand":{"translation":[-1,2.25,0],"scale":[0.66992,0.66992,0.66992]},"firstperson_lefthand":{"translation":[-1,2.25,0],"scale":[0.66992,0.66992,0.66992]},"ground":{"translation":[0,3.75,0],"scale":[0.55273,0.55273,0.55273]},"gui":{"rotation":[-180,51.75,-180],"translation":[-0.5,-2.5,0],"scale":[0.625,0.625,0.625]},"head":{"translation":[0,-19.25,-6],"scale":[0,0,0]},"fixed":{"rotation":[-90,0,0],"translation":[0,-5,-20.75],"scale":[2.5957,2.5957,2.5957]}},"groups":[{"name":"group","origin":[8,8,8],"color":0,"children":[0,1,2,3,4,5,6,7,8,9,10,11,12,13]}]}