{
	"credit": "MadewithBlockbench",
	"texture_size": [32, 32],
	"textures": {
		"1": "morefunnyitems:block/jf/bas_jf_kantana-stand"
	},
	"elements": [
		{
			"from": [0.017, 8.79266, 7.14],
			"to": [3.017, 9.79266, 9.14],
			"rotation": {"angle": 0, "axis": "y", "origin": [0.98, 9.02666, 8.037]},
			"faces": {
				"north": {"uv": [1.5, 1.5, 3, 2], "texture": "#1"},
				"east": {"uv": [1.5, 2, 2.5, 2.5], "texture": "#1"},
				"south": {"uv": [1.5, 1.5, 3, 2], "texture": "#1"},
				"west": {"uv": [1.5, 2, 2.5, 2.5], "texture": "#1"},
				"up": {"uv": [3, 1.5, 1.5, 0.5], "texture": "#1"},
				"down": {"uv": [3, 0.5, 1.5, 1.5], "texture": "#1"}
			}
		},
		{
			"from": [1.487, -1.74381, 5.53681],
			"to": [2.487, 12.25619, 6.53681],
			"rotation": {"angle": 22.5, "axis": "x", "origin": [0.98, 3.62196, 8.07603]},
			"faces": {
				"north": {"uv": [1.5, 2.5, 2, 9.5], "texture": "#1"},
				"east": {"uv": [1.5, 2.5, 2, 9.5], "texture": "#1"},
				"south": {"uv": [1.5, 2.5, 2, 9.5], "texture": "#1"},
				"west": {"uv": [1.5, 2.5, 2, 9.5], "texture": "#1"},
				"up": {"uv": [2, 9.5, 1.5, 10], "texture": "#1"},
				"down": {"uv": [2, 9.5, 1.5, 10], "texture": "#1"}
			}
		},
		{
			"from": [0.473, -1.74381, 9.60126],
			"to": [1.473, 12.25619, 10.60126],
			"rotation": {"angle": -22.5, "axis": "x", "origin": [0.98, 3.62196, 8.07603]},
			"faces": {
				"north": {"uv": [1.5, 2.5, 2, 9.5], "texture": "#1"},
				"east": {"uv": [1.5, 2.5, 2, 9.5], "texture": "#1"},
				"south": {"uv": [1.5, 2.5, 2, 9.5], "texture": "#1"},
				"west": {"uv": [1.5, 2.5, 2, 9.5], "texture": "#1"},
				"up": {"uv": [2, 9.5, 1.5, 10], "texture": "#1"},
				"down": {"uv": [2, 9.5, 1.5, 10], "texture": "#1"}
			}
		},
		{
			"from": [13.499, -1.74381, 5.53681],
			"to": [14.499, 12.25619, 6.53681],
			"rotation": {"angle": 22.5, "axis": "x", "origin": [15.02, 3.62196, 8.07603]},
			"faces": {
				"north": {"uv": [1.5, 2.5, 2, 9.5], "texture": "#1"},
				"east": {"uv": [1.5, 2.5, 2, 9.5], "texture": "#1"},
				"south": {"uv": [1.5, 2.5, 2, 9.5], "texture": "#1"},
				"west": {"uv": [1.5, 2.5, 2, 9.5], "texture": "#1"},
				"up": {"uv": [2, 9.5, 1.5, 10], "texture": "#1"},
				"down": {"uv": [2, 9.5, 1.5, 10], "texture": "#1"}
			}
		},
		{
			"from": [13.043, 8.79266, 7.14],
			"to": [16.043, 9.79266, 9.14],
			"rotation": {"angle": 0, "axis": "y", "origin": [15.02, 9.02666, 8.037]},
			"faces": {
				"north": {"uv": [1.5, 1.5, 3, 2], "texture": "#1"},
				"east": {"uv": [1.5, 2, 2.5, 2.5], "texture": "#1"},
				"south": {"uv": [1.5, 1.5, 3, 2], "texture": "#1"},
				"west": {"uv": [1.5, 2, 2.5, 2.5], "texture": "#1"},
				"up": {"uv": [3, 1.5, 1.5, 0.5], "texture": "#1"},
				"down": {"uv": [3, 0.5, 1.5, 1.5], "texture": "#1"}
			}
		},
		{
			"from": [14.513, -1.74381, 9.60126],
			"to": [15.513, 12.25619, 10.60126],
			"rotation": {"angle": -22.5, "axis": "x", "origin": [15.02, 3.62196, 8.07603]},
			"faces": {
				"north": {"uv": [1.5, 2.5, 2, 9.5], "texture": "#1"},
				"east": {"uv": [1.5, 2.5, 2, 9.5], "texture": "#1"},
				"south": {"uv": [1.5, 2.5, 2, 9.5], "texture": "#1"},
				"west": {"uv": [1.5, 2.5, 2, 9.5], "texture": "#1"},
				"up": {"uv": [2, 9.5, 1.5, 10], "texture": "#1"},
				"down": {"uv": [2, 9.5, 1.5, 10], "texture": "#1"}
			}
		},
		{
			"from": [-2.04578, 11.07096, 7.87681],
			"to": [17.95422, 12.07096, 8.87681],
			"rotation": {"angle": -45, "axis": "x", "origin": [2.08822, 11.18796, 8.38381]},
			"faces": {
				"north": {"uv": [2, 0, 12, 0.5], "texture": "#1"},
				"east": {"uv": [1.5, 0, 2, 0.5], "texture": "#1"},
				"south": {"uv": [2, 0, 12, 0.5], "texture": "#1"},
				"west": {"uv": [1.5, 0, 2, 0.5], "texture": "#1"},
				"up": {"uv": [2, 0, 12, 0.5], "texture": "#1"},
				"down": {"uv": [2, 0, 12, 0.5], "texture": "#1"}
			}
		},
		{
			"from": [4.49, -0.74604, 5.42403],
			"to": [5.49, 18.25396, 6.42403],
			"rotation": {"angle": 22.5, "axis": "x", "origin": [8, 8.69196, 4.95603]},
			"faces": {
				"north": {"uv": [1, 0, 1.5, 9.5], "texture": "#1"},
				"east": {"uv": [1, 0, 1.5, 9.5], "texture": "#1"},
				"south": {"uv": [1, 0, 1.5, 9.5], "texture": "#1"},
				"west": {"uv": [1, 0, 1.5, 9.5], "texture": "#1"},
				"up": {"uv": [1.5, 10, 1, 9.5], "texture": "#1"},
				"down": {"uv": [1.5, 9.5, 1, 10], "texture": "#1"}
			}
		},
		{
			"from": [7.61, -0.74604, 5.42403],
			"to": [8.61, 20.25396, 6.42403],
			"rotation": {"angle": 22.5, "axis": "x", "origin": [8, 8.69196, 4.95603]},
			"faces": {
				"north": {"uv": [0.5, 0, 1, 10.5], "texture": "#1"},
				"east": {"uv": [0.5, 0, 1, 10.5], "texture": "#1"},
				"south": {"uv": [0.5, 0, 1, 10.5], "texture": "#1"},
				"west": {"uv": [0.5, 0, 1, 10.5], "texture": "#1"},
				"up": {"uv": [1.5, 10.5, 1, 10], "texture": "#1"},
				"down": {"uv": [1.5, 10, 1, 10.5], "texture": "#1"}
			}
		},
		{
			"from": [10.574, -0.74604, 5.42403],
			"to": [11.574, 22.25396, 6.42403],
			"rotation": {"angle": 22.5, "axis": "x", "origin": [8, 8.69196, 4.95603]},
			"faces": {
				"north": {"uv": [0, 0, 0.5, 11.5], "texture": "#1"},
				"east": {"uv": [0, 0, 0.5, 11.5], "texture": "#1"},
				"south": {"uv": [0, 0, 0.5, 11.5], "texture": "#1"},
				"west": {"uv": [0, 0, 0.5, 11.5], "texture": "#1"},
				"up": {"uv": [1.5, 11, 1, 10.5], "texture": "#1"},
				"down": {"uv": [1.5, 10.5, 1, 11], "texture": "#1"}
			}
		},
		{
			"from": [10.0628, 23.70575, -5.43867],
			"to": [12.0628, 24.70575, -3.43867],
			"rotation": {"angle": 22.5, "axis": "x", "origin": [1.83488, -16.18521, -7.28011]},
			"faces": {
				"north": {"uv": [3, 1.5, 4, 2], "texture": "#1"},
				"east": {"uv": [3, 1.5, 4, 2], "texture": "#1"},
				"south": {"uv": [3, 1.5, 4, 2], "texture": "#1"},
				"west": {"uv": [3, 1.5, 4, 2], "texture": "#1"},
				"up": {"uv": [4, 1.5, 3, 0.5], "texture": "#1"},
				"down": {"uv": [4, 0.5, 3, 1.5], "texture": "#1"}
			}
		},
		{
			"from": [10.824, 21.87854, 7.02645],
			"to": [11.324, 26.87854, 8.02645],
			"rotation": {"angle": 22.5, "axis": "x", "origin": [8.68352, 12.53221, 6.70091]},
			"faces": {
				"north": {"uv": [0.25, 11.5, 0.5, 14], "texture": "#1"},
				"east": {"uv": [1, 11.5, 1.5, 14], "texture": "#1"},
				"south": {"uv": [0.25, 11.5, 0.5, 14], "texture": "#1"},
				"west": {"uv": [1, 11.5, 1.5, 14], "texture": "#1"},
				"up": {"uv": [1.25, 11.5, 1, 11], "texture": "#1"},
				"down": {"uv": [1.25, 11, 1, 11.5], "texture": "#1"}
			}
		},
		{
			"from": [7.86, 19.83287, 7.25606],
			"to": [8.36, 24.83287, 8.25606],
			"rotation": {"angle": 22.5, "axis": "x", "origin": [8.71952, 13.08654, 6.93052]},
			"faces": {
				"north": {"uv": [0, 11.5, 0.25, 14], "texture": "#1"},
				"east": {"uv": [0.5, 10.5, 1, 13], "texture": "#1"},
				"south": {"uv": [0, 11.5, 0.25, 14], "texture": "#1"},
				"west": {"uv": [0.5, 10.5, 1, 13], "texture": "#1"},
				"up": {"uv": [1.5, 11.5, 1.25, 11], "texture": "#1"},
				"down": {"uv": [1.5, 11, 1.25, 11.5], "texture": "#1"}
			}
		},
		{
			"from": [4.74, 17.81004, 7.37087],
			"to": [5.24, 22.81004, 8.37087],
			"rotation": {"angle": 22.5, "axis": "x", "origin": [8.89952, 13.36371, 7.04533]},
			"faces": {
				"north": {"uv": [0, 11.5, 0.25, 14], "texture": "#1"},
				"east": {"uv": [0.5, 10.5, 1, 13], "texture": "#1"},
				"south": {"uv": [0, 11.5, 0.25, 14], "texture": "#1"},
				"west": {"uv": [0.5, 10.5, 1, 13], "texture": "#1"},
				"up": {"uv": [0.75, 13.5, 0.5, 13], "texture": "#1"},
				"down": {"uv": [0.75, 13, 0.5, 13.5], "texture": "#1"}
			}
		}
	],
	"display": {
		"thirdperson_righthand": {
			"scale": [0.36, 0.36, 0.36]
		},
		"thirdperson_lefthand": {
			"scale": [0.36, 0.36, 0.36]
		},
		"firstperson_righthand": {
			"scale": [0, 0, 0]
		},
		"firstperson_lefthand": {
			"scale": [0, 0, 0]
		},
		"ground": {
			"scale": [0.34, 0.34, 0.34]
		},
		"gui": {
			"rotation": [-150.75, 24, -180],
			"translation": [0, -2, 0],
			"scale": [0.45, 0.45, 0.45]
		},
		"head": {
			"translation": [0, -23, 0],
			"scale": [2.47, 2.49, 2.52]
		},
		"fixed": {
			"rotation": [-90, 0, 0],
			"translation": [0, 0.25, -21.5],
			"scale": [2.5, 2.5, 2.5]
		}
	}
}